denoiser/__init__.py
denoiser/audio.py
denoiser/augment.py
denoiser/data.py
denoiser/demucs.py
denoiser/distrib.py
denoiser/dsp.py
denoiser/enhance.py
denoiser/evaluate.py
denoiser/executor.py
denoiser/live.py
denoiser/pretrained.py
denoiser/resample.py
denoiser/solver.py
denoiser/stft_loss.py
denoiser/utils.py
denoiser_compat-0.1.5.dev0.dist-info/LICENSE
denoiser_compat-0.1.5.dev0.dist-info/METADATA
denoiser_compat-0.1.5.dev0.dist-info/WHEEL
denoiser_compat-0.1.5.dev0.dist-info/top_level.txt
denoiser_compat-0.1.5.dev0.dist-info/RECORD
